nsx/__init__.py
nsx/config.py
nsx/learner.py
nsx/loss.py
nsx/agent/__init__.py
nsx/agent/discovery.py
nsx/agent/guard.py
nsx/agent/interface.py
nsx/agent/llm_interface.py
nsx/agent/prompts.py
nsx/agent/translator.py
nsx/bridge/__init__.py
nsx/bridge/concepts.py
nsx/bridge/reasoner.py
nsx/core/__init__.py
nsx/core/compiler.py
nsx/core/logic.py
nsx/core/symbols.py
nsx/core/tnorms.py
nsx_ai-1.0.2.dist-info/licenses/LICENSE
nsx_ai-1.0.2.dist-info/METADATA
nsx_ai-1.0.2.dist-info/WHEEL
nsx_ai-1.0.2.dist-info/top_level.txt
nsx_ai-1.0.2.dist-info/RECORD
